CODE_OF_CONDUCT.md
LICENSE
MANIFEST.in
README.md
pyproject.toml
setup.cfg
rhythmidia/__init__.py
rhythmidia/_version.py
rhythmidia/parameters.txt
rhythmidia/py.typed
rhythmidia/rhythmidia.py
rhythmidia/rhythmidia_gui.py
rhythmidia.egg-info/PKG-INFO
rhythmidia.egg-info/SOURCES.txt
rhythmidia.egg-info/dependency_links.txt
rhythmidia.egg-info/entry_points.txt
rhythmidia.egg-info/not-zip-safe
rhythmidia.egg-info/requires.txt
rhythmidia.egg-info/top_level.txt
rhythmidia/../images/icons/pelhamLogoSquare.jpg
rhythmidia/../images/icons/rhythmidiaLogoBannerText.jpg
rhythmidia/../images/icons/rhythmidiaLogoSquare.jpg
rhythmidia/tests/__init__.py
rhythmidia/tests/test_rhythmidia.py