Metadata-Version: 2.1
Name: rhythmidia
Version: 0.1.1
Summary: Race tube image analysis and period elucidation in Python.
Author-email: Alex Keeley <alex.k@wustl.edu>
License: MIT
Project-URL: Source, https://github.com/Pelham-Lab/rhythmidia/
Project-URL: Documentation, https://rhythmidia.readthedocs.io/
Classifier: License :: OSI Approved :: MIT License
Classifier: Programming Language :: Python :: 3
Requires-Python: >=3.11
License-File: LICENSE
Requires-Dist: importlib-resources; python_version >= "3.11"
Requires-Dist: numpy
Requires-Dist: matplotlib
Requires-Dist: scipy
Requires-Dist: pyautogui
Requires-Dist: scikit-image
Requires-Dist: guizero
Requires-Dist: pytest
Requires-Dist: PyWavelets
Provides-Extra: test
Requires-Dist: pytest>=6.1.2; extra == "test"
Requires-Dist: pytest-runner; extra == "test"
